gw_ui_streamlit/__init__.py
gw_ui_streamlit/_create_ui.py
gw_ui_streamlit/_utils.py
gw_ui_streamlit/cache.py
gw_ui_streamlit/constants.py
gw_ui_streamlit/core.py
gw_ui_streamlit/create_ui.py
gw_ui_streamlit/database.py
gw_ui_streamlit/dialog_ui.py
gw_ui_streamlit/independent_utils.py
gw_ui_streamlit/input_types/__init__.py
gw_ui_streamlit/input_types/button_inputs.py
gw_ui_streamlit/input_types/code_inputs.py
gw_ui_streamlit/input_types/date_inputs.py
gw_ui_streamlit/input_types/numeric_inputs.py
gw_ui_streamlit/input_types/other_inputs.py
gw_ui_streamlit/input_types/table_inputs.py
gw_ui_streamlit/input_types/text_inputs.py
gw_ui_streamlit/markdown.py
gw_ui_streamlit/process_templates.py
gw_ui_streamlit/tests/test_yaml_model.py
gw_ui_streamlit/utils.py
gw_ui_streamlit/yaml_model.py
gw_ui_streamlit-0.5.86.dist-info/METADATA
gw_ui_streamlit-0.5.86.dist-info/WHEEL
gw_ui_streamlit-0.5.86.dist-info/RECORD
