Metadata-Version: 2.3
Name: gw-ui-streamlit
Version: 0.5.86
Summary: GW Streamlit runtime environment
Author: Chris Moore
Author-email: cmoore@guidewire.com
Requires-Python: >=3.12
Classifier: Programming Language :: Python :: 3
Classifier: Programming Language :: Python :: 3.12
Classifier: Programming Language :: Python :: 3.13
Requires-Dist: cerberus (>=1.3.7,<2.0.0)
Requires-Dist: graphviz (>=0.20.3,<0.21.0)
Requires-Dist: gw-settings-management (>=0.5.3,<0.6.0)
Requires-Dist: jinja2 (>=3.1.5,<4.0.0)
Requires-Dist: pandas (>=2.2.3,<3.0.0)
Requires-Dist: pathvalidate (>=3.2.3,<4.0.0)
Requires-Dist: pydantic (>=2.10.6,<3.0.0)
Requires-Dist: pyyaml (>=6.0.2,<7.0.0)
Requires-Dist: streamlit (>=1.43.1,<2.0.0)
Requires-Dist: streamlit-ace (>=0.1.1,<0.2.0)
